atlassianforms/__init__.py
atlassianforms/client.py
atlassianforms/manager.py
atlassianforms/form/__init__.py
atlassianforms/form/manager.py
atlassianforms/form/parser.py
atlassianforms/models/__init__.py
atlassianforms/models/response.py
atlassianforms/validators/__init__.py
atlassianforms/validators/field.py
tests/__init__.py
tests/test_field_validator.py
tests/test_form_manager.py
tests/test_form_parser.py
tests/test_response.py
tests/test_service_desk_manager.py
atlassian_forms_submitter_sdk-1.1.3.dist-info/LICENSE
atlassian_forms_submitter_sdk-1.1.3.dist-info/METADATA
atlassian_forms_submitter_sdk-1.1.3.dist-info/WHEEL
atlassian_forms_submitter_sdk-1.1.3.dist-info/top_level.txt
atlassian_forms_submitter_sdk-1.1.3.dist-info/RECORD
